elvet/__init__.py
elvet/bc.py
elvet/domains.py
elvet/models.py
elvet/plotting.py
elvet/math/__init__.py
elvet/math/derivative.py
elvet/math/integral.py
elvet/math/diffops/__init__.py
elvet/math/diffops/first_order_ops.py
elvet/math/diffops/higher_order_ops.py
elvet/math/diffops/metric_ops.py
elvet/math/diffops/second_order_ops.py
elvet/minimizer/__init__.py
elvet/minimizer/_input_normalizer.py
elvet/minimizer/minimizer.py
elvet/solver/__init__.py
elvet/solver/_input_normalizer.py
elvet/solver/fitter.py
elvet/solver/solver.py
elvet/system/__init__.py
elvet/system/exceptions.py
elvet/system/logger.py
elvet/utils/LRschedulers.py
elvet/utils/__init__.py
elvet/utils/callbacks.py
elvet/utils/loss_combinators.py
elvet/utils/metrics.py
elvet/utils/unstack.py
elvet-1.0.2.dist-info/licenses/LICENSE
elvet-1.0.2.dist-info/METADATA
elvet-1.0.2.dist-info/WHEEL
elvet-1.0.2.dist-info/top_level.txt
elvet-1.0.2.dist-info/RECORD
