Metadata-Version: 2.4
Name: elvet
Version: 1.0.2
Summary: A neural network-based differential equation and variational problem solver
Home-page: https://gitlab.com/elvet/elvet
Author: J. Y. Araz, J. C. Criado, M. Spannowsky
Author-email: jack.araz@durham.ac.uk, criadoalamo@gmail.es, michael.spannowsky@durham.ac.uk
License: MIT
Classifier: Intended Audience :: Science/Research
Classifier: License :: OSI Approved :: MIT License
Classifier: Operating System :: OS Independent
Classifier: Programming Language :: Python :: 3
Classifier: Topic :: Scientific/Engineering :: Artificial Intelligence
Classifier: Topic :: Scientific/Engineering :: Mathematics
Classifier: Topic :: Scientific/Engineering :: Physics
Requires-Python: >=3.6
License-File: LICENSE
Dynamic: author
Dynamic: author-email
Dynamic: classifier
Dynamic: description
Dynamic: description-content-type
Dynamic: home-page
Dynamic: license
Dynamic: license-file
Dynamic: requires-python
Dynamic: summary
